fail_kit/__init__.py
fail_kit_fastapi-2.0.0.dist-info/METADATA
fail_kit_fastapi-2.0.0.dist-info/WHEEL
fail_kit_fastapi-2.0.0.dist-info/top_level.txt
fail_kit_fastapi-2.0.0.dist-info/RECORD
