Metadata-Version: 2.4
Name: fail-kit-fastapi
Version: 2.0.0
Summary: F.A.I.L. Kit - Forensic Audit of Intelligent Logic - FastAPI middleware
Author-email: "F.A.I.L. Kit" <ali@jakvan.io>
License: MIT
Project-URL: Homepage, https://github.com/resetroot99/The-FAIL-Kit
Project-URL: Documentation, https://github.com/resetroot99/The-FAIL-Kit/blob/main/docs/EASY_INTEGRATION.md
Project-URL: Repository, https://github.com/resetroot99/The-FAIL-Kit
Project-URL: Issues, https://github.com/resetroot99/The-FAIL-Kit/issues
Keywords: ai,audit,testing,agent,llm,fastapi,middleware
Classifier: Development Status :: 4 - Beta
Classifier: Intended Audience :: Developers
Classifier: License :: OSI Approved :: MIT License
Classifier: Programming Language :: Python :: 3
Classifier: Programming Language :: Python :: 3.9
Classifier: Programming Language :: Python :: 3.10
Classifier: Programming Language :: Python :: 3.11
Classifier: Programming Language :: Python :: 3.12
Classifier: Framework :: FastAPI
Classifier: Topic :: Software Development :: Testing
Classifier: Topic :: Scientific/Engineering :: Artificial Intelligence
Requires-Python: >=3.9
Provides-Extra: fastapi
Requires-Dist: fastapi>=0.100.0; extra == "fastapi"
Provides-Extra: dev
Requires-Dist: pytest; extra == "dev"
Requires-Dist: pytest-asyncio; extra == "dev"
Requires-Dist: httpx; extra == "dev"
